jaraco/test/__init__.py
jaraco/test/cpython.py
jaraco/test/http.py
jaraco/test/py.typed
jaraco.test-5.5.1.dist-info/LICENSE
jaraco.test-5.5.1.dist-info/METADATA
jaraco.test-5.5.1.dist-info/WHEEL
jaraco.test-5.5.1.dist-info/entry_points.txt
jaraco.test-5.5.1.dist-info/top_level.txt
jaraco.test-5.5.1.dist-info/RECORD
